LICENSE
statsdir/__init__.py
statsdir/__main__.py
statsdir/py.typed
statsdir-0.0.2.1.dist-info/LICENSE
statsdir-0.0.2.1.dist-info/METADATA
statsdir-0.0.2.1.dist-info/WHEEL
statsdir-0.0.2.1.dist-info/entry_points.txt
statsdir-0.0.2.1.dist-info/RECORD
