Metadata-Version: 2.1
Name: statsdir
Version: 0.0.2.1
Summary: statsdir.
Home-page: https://github.com/ChenyangGao/web-mount-packs/tree/main/python-module/statsdir
License: MIT
Keywords: statsdir,statistics
Author: ChenyangGao
Author-email: wosiwujm@gmail.com
Requires-Python: >=3.10,<4.0
Classifier: Development Status :: 5 - Production/Stable
Classifier: Intended Audience :: Developers
Classifier: License :: OSI Approved :: MIT License
Classifier: Operating System :: OS Independent
Classifier: Programming Language :: Python
Classifier: Programming Language :: Python :: 3
Classifier: Programming Language :: Python :: 3.10
Classifier: Programming Language :: Python :: 3.11
Classifier: Programming Language :: Python :: 3.12
Classifier: Programming Language :: Python :: 3 :: Only
Classifier: Topic :: Software Development
Classifier: Topic :: Software Development :: Libraries
Classifier: Topic :: Software Development :: Libraries :: Python Modules
Requires-Dist: iterdir (>=0.0.6)
Project-URL: Repository, https://github.com/ChenyangGao/web-mount-packs/tree/main/python-module/statsdir
